agentspec/__init__.py
agentspec/__main__.py
agentspec/cli/__init__.py
agentspec/cli/commands.py
agentspec/cli/completers.py
agentspec/cli/completion.py
agentspec/cli/completion_install.py
agentspec/cli/interactive.py
agentspec/cli/main.py
agentspec/config/__init__.py
agentspec/config/default.yaml
agentspec/config/logging.yaml
agentspec/core/__init__.py
agentspec/core/ai_integrator.py
agentspec/core/context_detector.py
agentspec/core/instruction_database.py
agentspec/core/spec_generator.py
agentspec/core/template_manager.py
agentspec/core/context/__init__.py
agentspec/core/context/framework_detector.py
agentspec/core/context/language_detector.py
agentspec/core/context/types.py
agentspec/core/instruction/__init__.py
agentspec/core/instruction/loader.py
agentspec/core/instruction/types.py
agentspec/core/instruction/validator.py
agentspec/data/__init__.py
agentspec/data/instructions/accessibility.json
agentspec/data/instructions/api-integration.json
agentspec/data/instructions/automation.json
agentspec/data/instructions/backend.json
agentspec/data/instructions/cloud.json
agentspec/data/instructions/compliance.json
agentspec/data/instructions/core.json
agentspec/data/instructions/database.json
agentspec/data/instructions/devops.json
agentspec/data/instructions/frontend.json
agentspec/data/instructions/integration.json
agentspec/data/instructions/mobile.json
agentspec/data/instructions/monitoring.json
agentspec/data/instructions/performance.json
agentspec/data/instructions/programming-languages.json
agentspec/data/instructions/reliability.json
agentspec/data/instructions/scalability.json
agentspec/data/instructions/testing.json
agentspec/data/schemas/agentspec-config.json
agentspec/data/schemas/ai-config.json
agentspec/data/schemas/instruction.json
agentspec/data/schemas/security.json
agentspec/data/schemas/template.json
agentspec/data/templates/architecture/enterprise-web-application.json
agentspec/data/templates/architecture/microservice.json
agentspec-2.1.1.dist-info/LICENSE
agentspec-2.1.1.dist-info/METADATA
agentspec-2.1.1.dist-info/WHEEL
agentspec-2.1.1.dist-info/entry_points.txt
agentspec-2.1.1.dist-info/top_level.txt
agentspec-2.1.1.dist-info/RECORD
