Metadata-Version: 2.2
Name: agentspec
Version: 2.1.1
Summary: Specification-driven development toolkit with smart context detection
Author-email: Keyur Golani <keyurrgolani@gmail.com>
License: MIT
Project-URL: Homepage, https://github.com/keyurgolani/AgentSpec
Project-URL: Documentation, https://github.com/keyurgolani/AgentSpec#readme
Project-URL: Repository, https://github.com/keyurgolani/AgentSpec.git
Project-URL: Bug Tracker, https://github.com/keyurgolani/AgentSpec/issues
Keywords: specification,development,automation,templates,cli
Classifier: Development Status :: 5 - Production/Stable
Classifier: Intended Audience :: Developers
Classifier: Operating System :: OS Independent
Classifier: Programming Language :: Python :: 3
Classifier: Programming Language :: Python :: 3.8
Classifier: Programming Language :: Python :: 3.9
Classifier: Programming Language :: Python :: 3.10
Classifier: Programming Language :: Python :: 3.11
Classifier: Programming Language :: Python :: 3.12
Classifier: Topic :: Software Development :: Code Generators
Classifier: Topic :: Software Development :: Documentation
Requires-Python: >=3.8
License-File: LICENSE
Requires-Dist: pyyaml>=6.0
Requires-Dist: jsonschema>=4.0.0
Requires-Dist: click>=8.0.0
Requires-Dist: rich<13.0.0,>=12.0.0
Requires-Dist: tomli>=1.2.0; python_version < "3.11"
Requires-Dist: argcomplete>=2.0.0
Provides-Extra: dev
Requires-Dist: pytest>=7.0.0; extra == "dev"
Requires-Dist: pytest-cov>=4.0.0; extra == "dev"
Requires-Dist: black<25.0.0,>=24.0.0; extra == "dev"
Requires-Dist: flake8<7.0.0,>=5.0.0; extra == "dev"
Requires-Dist: mypy<1.8.0,>=0.991; extra == "dev"
Requires-Dist: types-PyYAML>=6.0.0; extra == "dev"
Requires-Dist: types-jsonschema>=4.0.0; extra == "dev"
Requires-Dist: pre-commit<4.0.0,>=2.20.0; extra == "dev"
Requires-Dist: bandit<2.0.0,>=1.7.0; extra == "dev"
Requires-Dist: build<1.0.0,>=0.8.0; extra == "dev"
Requires-Dist: twine<5.0.0,>=4.0.0; extra == "dev"
Requires-Dist: isort<6.0.0,>=5.10.0; extra == "dev"
Provides-Extra: test
Requires-Dist: pytest<8.0.0,>=7.0.0; extra == "test"
Requires-Dist: pytest-cov<5.0.0,>=4.0.0; extra == "test"
Requires-Dist: pytest-mock<4.0.0,>=3.8.0; extra == "test"
Requires-Dist: pytest-timeout<3.0.0,>=2.1.0; extra == "test"
